{
  "attributes": [
    {
      "allow_nil?": false,
      "default": "fragment(\"uuid_generate_v7()\")",
      "generated?": false,
      "precision": null,
      "primary_key?": true,
      "references": null,
      "scale": null,
      "size": null,
      "source": "id",
      "type": "uuid"
    },
    {
      "allow_nil?": false,
      "default": "nil",
      "generated?": false,
      "precision": null,
      "primary_key?": false,
      "references": null,
      "scale": null,
      "size": null,
      "source": "metric_type",
      "type": "text"
    },
    {
      "allow_nil?": false,
      "default": "nil",
      "generated?": false,
      "precision": null,
      "primary_key?": false,
      "references": null,
      "scale": null,
      "size": null,
      "source": "value",
      "type": "decimal"
    },
    {
      "allow_nil?": false,
      "default": "nil",
      "generated?": false,
      "precision": null,
      "primary_key?": false,
      "references": null,
      "scale": null,
      "size": null,
      "source": "unit",
      "type": "text"
    },
    {
      "allow_nil?": true,
      "default": "%{}",
      "generated?": false,
      "precision": null,
      "primary_key?": false,
      "references": null,
      "scale": null,
      "size": null,
      "source": "metadata",
      "type": "map"
    },
    {
      "allow_nil?": false,
      "default": "nil",
      "generated?": false,
      "precision": null,
      "primary_key?": false,
      "references": null,
      "scale": null,
      "size": null,
      "source": "team_id",
      "type": "uuid"
    },
    {
      "allow_nil?": false,
      "default": "fragment(\"(now() AT TIME ZONE 'utc')\")",
      "generated?": false,
      "precision": null,
      "primary_key?": false,
      "references": null,
      "scale": null,
      "size": null,
      "source": "recorded_at",
      "type": "utc_datetime_usec"
    },
    {
      "allow_nil?": false,
      "default": "nil",
      "generated?": false,
      "precision": null,
      "primary_key?": false,
      "references": {
        "deferrable": false,
        "destination_attribute": "id",
        "destination_attribute_default": null,
        "destination_attribute_generated": null,
        "index?": true,
        "match_type": null,
        "match_with": null,
        "multitenancy": {
          "attribute": "team_id",
          "global": false,
          "strategy": "attribute"
        },
        "name": "service_metrics_service_instance_id_fkey",
        "on_delete": "delete",
        "on_update": null,
        "primary_key?": true,
        "schema": null,
        "table": "container_service_instances"
      },
      "scale": null,
      "size": null,
      "source": "service_instance_id",
      "type": "uuid"
    }
  ],
  "base_filter": null,
  "check_constraints": [],
  "custom_indexes": [
    {
      "all_tenants?": false,
      "concurrently": false,
      "error_fields": [
        "service_instance_id",
        "metric_type",
        "recorded_at"
      ],
      "fields": [
        {
          "type": "atom",
          "value": "service_instance_id"
        },
        {
          "type": "atom",
          "value": "metric_type"
        },
        {
          "type": "atom",
          "value": "recorded_at"
        }
      ],
      "include": null,
      "message": null,
      "name": null,
      "nulls_distinct": true,
      "prefix": null,
      "table": null,
      "unique": false,
      "using": null,
      "where": null
    }
  ],
  "custom_statements": [],
  "has_create_action": true,
  "hash": "FB9844A34712AE276C7BB27E838431CD284158099DE3A3644FBCB0982A34595B",
  "identities": [],
  "multitenancy": {
    "attribute": "team_id",
    "global": false,
    "strategy": "attribute"
  },
  "repo": "Elixir.Dirup.Repo",
  "schema": null,
  "table": "service_metrics"
}